[
  { "id": 1, "name": "Pizza" },
  { "id": 2, "name": "Sushi" },
  { "id": 3, "name": "Burger" },
  { "id": 4, "name": "Ramen" },
  { "id": 5, "name": "Tacos" },
  { "id": 6, "name": "Fried Chicken" },
  { "id": 7, "name": "Pasta" },
  { "id": 8, "name": "Curry" },
  { "id": 9, "name": "Dim Sum" },
  { "id": 10, "name": "Paella" },
  { "id": 11, "name": "Pho" },
  { "id": 12, "name": "Biryani" },
  { "id": 13, "name": "Dumplings" },
  { "id": 14, "name": "Pad Thai" },
  { "id": 15, "name": "Croissant" },
  { "id": 16, "name": "Sashimi" },
  { "id": 17, "name": "Burrito" },
  { "id": 18, "name": "Donuts" },
  { "id": 19, "name": "Falafel" },
  { "id": 20, "name": "Shawarma" },
  { "id": 21, "name": "Hot Dog" },
  { "id": 22, "name": "Kebab" },
  { "id": 23, "name": "Gyoza" },
  { "id": 24, "name": "Moussaka" },
  { "id": 25, "name": "Peking Duck" },
  { "id": 26, "name": "Tom Yum Goong" },
  { "id": 27, "name": "Churros" },
  { "id": 28, "name": "Barbecue Ribs" },
  { "id": 29, "name": "Ceviche" },
  { "id": 30, "name": "Kimchi" },
  { "id": 31, "name": "Goulash" },
  { "id": 32, "name": "Tortilla" },
  { "id": 33, "name": "Banh Mi" },
  { "id": 34, "name": "Chicken Tikka Masala" },
  { "id": 35, "name": "Fish and Chips" },
  { "id": 36, "name": "Lasagna" },
  { "id": 37, "name": "Enchiladas" },
  { "id": 38, "name": "Fajitas" },
  { "id": 39, "name": "Couscous" },
  { "id": 40, "name": "Hummus" },
  { "id": 41, "name": "Macaroni and Cheese" },
  { "id": 42, "name": "Spring Rolls" },
  { "id": 43, "name": "Pancakes" },
  { "id": 44, "name": "Waffles" },
  { "id": 45, "name": "Cheesecake" },
  { "id": 46, "name": "Tiramisu" },
  { "id": 47, "name": "Ice Cream" },
  { "id": 48, "name": "Chocolate Cake" },
  { "id": 49, "name": "Brownies" },
  { "id": 50, "name": "Apple Pie" },
  { "id": 51, "name": "Baklava" },
  { "id": 52, "name": "Crepes" },
  { "id": 53, "name": "Empanadas" },
  { "id": 54, "name": "Samosa" },
  { "id": 55, "name": "Onion Rings" },
  { "id": 56, "name": "Nachos" },
  { "id": 57, "name": "Guacamole" },
  { "id": 58, "name": "Bruschetta" },
  { "id": 59, "name": "Gazpacho" },
  { "id": 60, "name": "Clam Chowder" },
  { "id": 61, "name": "Lobster Roll" },
  { "id": 62, "name": "Seafood Paella" },
  { "id": 63, "name": "Risotto" },
  { "id": 64, "name": "Stuffed Peppers" },
  { "id": 65, "name": "Meatballs" },
  { "id": 66, "name": "Shepherd's Pie" },
  { "id": 67, "name": "Beef Stroganoff" },
  { "id": 68, "name": "Cornbread" },
  { "id": 69, "name": "Biscuits and Gravy" },
  { "id": 70, "name": "Jambalaya" },
  { "id": 71, "name": "Gumbo" },
  { "id": 72, "name": "Chili" },
  { "id": 73, "name": "Poutine" },
  { "id": 74, "name": "Maple Syrup Pancakes" },
  { "id": 75, "name": "Beef Wellington" },
  { "id": 76, "name": "Roast Beef" },
  { "id": 77, "name": "Yorkshire Pudding" },
  { "id": 78, "name": "Bangers and Mash" },
  { "id": 79, "name": "Toad in the Hole" },
  { "id": 80, "name": "Haggis" },
  { "id": 81, "name": "Black Pudding" },
  { "id": 82, "name": "Scotch Egg" },
  { "id": 83, "name": "Crumpets" },
  { "id": 84, "name": "Scones" },
  { "id": 85, "name": "Cornish Pasty" },
  { "id": 86, "name": "Welsh Rarebit" },
  { "id": 87, "name": "Irish Stew" },
  { "id": 88, "name": "Boxty" },
  { "id": 89, "name": "Colcannon" },
  { "id": 90, "name": "Fried Cod" },
  { "id": 91, "name": "Sauerbraten" },
  { "id": 92, "name": "Bratwurst" },
  { "id": 93, "name": "Pretzel" },
  { "id": 94, "name": "Schnitzel" },
  { "id": 95, "name": "Goulash Soup" },
  { "id": 96, "name": "Pierogi" },
  { "id": 97, "name": "Borscht" },
  { "id": 98, "name": "Pelmeni" },
  { "id": 99, "name": "Blini" },
  { "id": 100, "name": "Kielbasa" },
  { "id": 101, "name": "Fried Rice" },
  { "id": 102, "name": "Beef Tacos" },
  { "id": 103, "name": "Chicken Quesadilla" },
  { "id": 104, "name": "Lobster Thermidor" },
  { "id": 105, "name": "Chicken Alfredo" },
  { "id": 106, "name": "BBQ Chicken Pizza" },
  { "id": 107, "name": "Shrimp Scampi" },
  { "id": 108, "name": "Spaghetti Carbonara" },
  { "id": 109, "name": "Mushroom Risotto" },
  { "id": 110, "name": "Meatloaf" },
  { "id": 111, "name": "Potato Salad" },
  { "id": 112, "name": "Chicken Caesar Salad" },
  { "id": 113, "name": "Tuna Melt" },
  { "id": 114, "name": "Club Sandwich" },
  { "id": 115, "name": "Grilled Cheese" },
  { "id": 116, "name": "French Fries" },
  { "id": 117, "name": "Chicken Nuggets" },
  { "id": 118, "name": "Mozzarella Sticks" },
  { "id": 119, "name": "Deviled Eggs" },
  { "id": 120, "name": "Garlic Bread" },
  { "id": 121, "name": "Caesar Salad" },
  { "id": 122, "name": "Caprese Salad" },
  { "id": 123, "name": "Cobb Salad" },
  { "id": 124, "name": "Greek Salad" },
  { "id": 125, "name": "Tabouleh" },
  { "id": 126, "name": "Potato Soup" },
  { "id": 127, "name": "Tomato Soup" },
  { "id": 128, "name": "French Onion Soup" },
  { "id": 129, "name": "Lentil Soup" },
  { "id": 130, "name": "Chicken Noodle Soup" },
  { "id": 131, "name": "Miso Soup" },
  { "id": 132, "name": "Egg Drop Soup" },
  { "id": 133, "name": "Wonton Soup" },
  { "id": 134, "name": "Fish Tacos" },
  { "id": 135, "name": "Veggie Burger" },
  { "id": 136, "name": "Chicken Wings" },
  { "id": 137, "name": "Teriyaki Chicken" },
  { "id": 138, "name": "Mongolian Beef" },
  { "id": 139, "name": "Sesame Chicken" },
  { "id": 140, "name": "Orange Chicken" },
  { "id": 141, "name": "Sweet and Sour Pork" },
  { "id": 142, "name": "General Tso's Chicken" },
  { "id": 143, "name": "Beef and Broccoli" },
  { "id": 144, "name": "Shrimp Fried Rice" },
  { "id": 145, "name": "Vegetable Stir Fry" },
  { "id": 146, "name": "Chow Mein" },
  { "id": 147, "name": "Lo Mein" },
  { "id": 148, "name": "Tofu Stir Fry" },
  { "id": 149, "name": "Baked Ziti" },
  { "id": 150, "name": "Manicotti" },
  { "id": 151, "name": "Chicken Parmesan" },
  { "id": 152, "name": "Eggplant Parmesan" },
  { "id": 153, "name": "Stuffed Shells" },
  { "id": 154, "name": "Tortellini Alfredo" },
  { "id": 155, "name": "Pesto Pasta" },
  { "id": 156, "name": "Fettuccine Alfredo" },
  { "id": 157, "name": "Spaghetti Bolognese" },
  { "id": 158, "name": "Cannelloni" },
  { "id": 159, "name": "Pasta Primavera" },
  { "id": 160, "name": "Pasta Puttanesca" },
  { "id": 161, "name": "Carbonara Pizza" },
  { "id": 162, "name": "Pepperoni Pizza" },
  { "id": 163, "name": "Margherita Pizza" },
  { "id": 164, "name": "Veggie Pizza" },
  { "id": 165, "name": "Hawaiian Pizza" },
  { "id": 166, "name": "Meat Lovers Pizza" },
  { "id": 167, "name": "Supreme Pizza" },
  { "id": 168, "name": "White Pizza" },
  { "id": 169, "name": "Calzone" },
  { "id": 170, "name": "Stromboli" },
  { "id": 171, "name": "Chicken Pot Pie" },
  { "id": 172, "name": "Beef Pot Pie" },
  { "id": 173, "name": "Turkey Sandwich" },
  { "id": 174, "name": "BLT Sandwich" },
  { "id": 175, "name": "Reuben Sandwich" },
  { "id": 176, "name": "Philly Cheesesteak" },
  { "id": 177, "name": "Pulled Pork Sandwich" },
  { "id": 178, "name": "Sloppy Joe" },
  { "id": 179, "name": "Meat Loaf" },
  { "id": 180, "name": "Pastrami on Rye" },
  { "id": 181, "name": "Ham and Cheese Sandwich" },
  { "id": 182, "name": "Roast Beef Sandwich" },
  { "id": 183, "name": "Avocado Toast" },
  { "id": 184, "name": "Bagel with Lox" },
  { "id": 185, "name": "Bagel and Cream Cheese" },
  { "id": 186, "name": "Breakfast Burrito" },
  { "id": 187, "name": "Breakfast Sandwich" },
  { "id": 188, "name": "French Toast" },
  { "id": 189, "name": "Scrambled Eggs" },
  { "id": 190, "name": "Omelette" },
  { "id": 191, "name": "Eggs Benedict" },
  { "id": 192, "name": "Poached Eggs" },
  { "id": 193, "name": "Sunny Side Up Eggs" },
  { "id": 194, "name": "Fried Eggs" },
  { "id": 195, "name": "Hard Boiled Eggs" },
  { "id": 196, "name": "Soft Boiled Eggs" },
  { "id": 197, "name": "Quiche" },
  { "id": 198, "name": "Frittata" },
  { "id": 199, "name": "Huevos Rancheros" },
  { "id": 200, "name": "Rotisserie Chicken" },
  { "id": 201, "name": "Chicken Fried Steak" },
  { "id": 202, "name": "Fried Green Tomatoes" },
  { "id": 203, "name": "Grits" },
  { "id": 204, "name": "Shrimp and Grits" },
  { "id": 205, "name": "Corn on the Cob" },
  { "id": 206, "name": "Baked Beans" },
  { "id": 207, "name": "Green Bean Casserole" },
  { "id": 208, "name": "Mashed Potatoes" },
  { "id": 209, "name": "Gravy" },
  { "id": 210, "name": "Roast Chicken" },
  { "id": 211, "name": "Roast Turkey" },
  { "id": 212, "name": "Cranberry Sauce" },
  { "id": 213, "name": "Stuffing" },
  { "id": 214, "name": "Deviled Ham" },
  { "id": 215, "name": "Tuna Casserole" },
  { "id": 216, "name": "Chicken Casserole" },
  { "id": 217, "name": "Green Salad" },
  { "id": 218, "name": "Garden Salad" },
  { "id": 219, "name": "Chef Salad" },
  { "id": 220, "name": "Taco Salad" },
  { "id": 221, "name": "Beet Salad" },
  { "id": 222, "name": "Spinach Salad" },
  { "id": 223, "name": "Arugula Salad" },
  { "id": 224, "name": "Watermelon Salad" },
  { "id": 225, "name": "Pasta Salad" },
  { "id": 226, "name": "Caesar Wrap" },
  { "id": 227, "name": "Chicken Wrap" },
  { "id": 228, "name": "Veggie Wrap" },
  { "id": 229, "name": "Turkey Wrap" },
  { "id": 230, "name": "Falafel Wrap" },
  { "id": 231, "name": "Hummus Wrap" },
  { "id": 232, "name": "Tuna Wrap" },
  { "id": 233, "name": "BBQ Wrap" },
  { "id": 234, "name": "Bacon Cheeseburger" },
  { "id": 235, "name": "Cheeseburger" },
  { "id": 236, "name": "Double Cheeseburger" },
  { "id": 237, "name": "Teriyaki Tofu" },
  { "id": 238, "name": "Grilled Tofu" },
  { "id": 239, "name": "Fried Tofu" },
  { "id": 240, "name": "Tofu Curry" },
  { "id": 241, "name": "Lentil Curry" },
  { "id": 242, "name": "Chickpea Curry" },
  { "id": 243, "name": "Potato Curry" },
  { "id": 244, "name": "Vegetable Curry" },
  { "id": 245, "name": "Chicken Korma" },
  { "id": 246, "name": "Rogan Josh" },
  { "id": 247, "name": "Vindaloo" },
  { "id": 248, "name": "Saag Paneer" },
  { "id": 249, "name": "Paneer Tikka" },
  { "id": 250, "name": "Maki Roll" },
  { "id": 251, "name": "Tempura" },
  { "id": 252, "name": "California Roll" },
  { "id": 253, "name": "Dragon Roll" },
  { "id": 254, "name": "Tuna Roll" },
  { "id": 255, "name": "Salmon Roll" },
  { "id": 256, "name": "Rainbow Roll" },
  { "id": 257, "name": "Udon Noodles" },
  { "id": 258, "name": "Yakisoba" },
  { "id": 259, "name": "Okonomiyaki" },
  { "id": 260, "name": "Takoyaki" },
  { "id": 261, "name": "Katsudon" },
  { "id": 262, "name": "Omurice" },
  { "id": 263, "name": "Karaage" },
  { "id": 264, "name": "Tonkatsu" },
  { "id": 265, "name": "Yakitori" },
  { "id": 266, "name": "Unagi Don" },
  { "id": 267, "name": "Chirashi" },
  { "id": 268, "name": "Hiyayakko" },
  { "id": 269, "name": "Natto" },
  { "id": 270, "name": "Tteokbokki" },
  { "id": 271, "name": "Bulgogi" },
  { "id": 272, "name": "Japchae" },
  { "id": 273, "name": "Bibimbap" },
  { "id": 274, "name": "Samgyeopsal" },
  { "id": 275, "name": "Kimbap" },
  { "id": 276, "name": "Gamjatang" },
  { "id": 277, "name": "Sundubu Jjigae" },
  { "id": 278, "name": "Kimchi Jjigae" },
  { "id": 279, "name": "Jajangmyeon" },
  { "id": 280, "name": "Galbi" },
  { "id": 281, "name": "Dak Galbi" },
  { "id": 282, "name": "Mandu" },
  { "id": 283, "name": "Soondae" },
  { "id": 284, "name": "Haemul Pajeon" },
  { "id": 285, "name": "Hotteok" },
  { "id": 286, "name": "Corn Dogs" },
  { "id": 287, "name": "Chicken Satay" },
  { "id": 288, "name": "Beef Satay" },
  { "id": 289, "name": "Nasi Goreng" },
  { "id": 290, "name": "Mee Goreng" },
  { "id": 291, "name": "Laksa" },
  { "id": 292, "name": "Rendang" },
  { "id": 293, "name": "Gado Gado" },
  { "id": 294, "name": "Soto Ayam" },
  { "id": 295, "name": "Ayam Penyet" },
  { "id": 296, "name": "Bakso" },
  { "id": 297, "name": "Siomay" },
  { "id": 298, "name": "Martabak" },
  { "id": 299, "name": "Nasi Uduk" },
  { "id": 300, "name": "Nasi Lemak" },
  { "id": 301, "name": "Char Kway Teow" },
  { "id": 302, "name": "Hainanese Chicken Rice" },
  { "id": 303, "name": "Bak Kut Teh" },
  { "id": 304, "name": "Mee Rebus" },
  { "id": 305, "name": "Mee Siam" },
  { "id": 306, "name": "Roti Canai" },
  { "id": 307, "name": "Roti Prata" },
  { "id": 308, "name": "Teh Tarik" },
  { "id": 309, "name": "Beef Pho" },
  { "id": 310, "name": "Bun Cha" },
  { "id": 311, "name": "Bun Bo Hue" },
  { "id": 312, "name": "Com Tam" },
  { "id": 313, "name": "Banh Xeo" },
  { "id": 314, "name": "Goi Cuon" },
  { "id": 315, "name": "Cha Ca" },
  { "id": 316, "name": "Mi Quang" },
  { "id": 317, "name": "Xoi" },
  { "id": 318, "name": "Ca Kho To" },
  { "id": 319, "name": "Thit Kho" },
  { "id": 320, "name": "Ga Nuong" },
  { "id": 321, "name": "Canh Chua" },
  { "id": 322, "name": "Bot Chien" },
  { "id": 323, "name": "Nem Ran" },
  { "id": 324, "name": "Nuoc Cham" },
  { "id": 325, "name": "Fish Amok" },
  { "id": 326, "name": "Lok Lak" },
  { "id": 327, "name": "Bai Sach Chrouk" },
  { "id": 328, "name": "Kuy Teav" },
  { "id": 329, "name": "Nom Banh Chok" },
  { "id": 330, "name": "Lap Khmer" },
  { "id": 331, "name": "Samlor Korkor" },
  { "id": 332, "name": "Balut" },
  { "id": 333, "name": "Adobo" },
  { "id": 334, "name": "Sinigang" },
  { "id": 335, "name": "Kare Kare" },
  { "id": 336, "name": "Lechon" },
  { "id": 337, "name": "Lumpia" },
  { "id": 338, "name": "Pancit" },
  { "id": 339, "name": "Tocino" },
  { "id": 340, "name": "Tapa" },
  { "id": 341, "name": "Bicol Express" },
  { "id": 342, "name": "Menudo" },
  { "id": 343, "name": "Tinola" },
  { "id": 344, "name": "Laing" },
  { "id": 345, "name": "Longganisa" },
  { "id": 346, "name": "Halo-Halo" },
  { "id": 347, "name": "Bibingka" },
  { "id": 348, "name": "Puto" },
  { "id": 349, "name": "Turon" },
  { "id": 350, "name": "Chicken Biryani" },
  { "id": 351, "name": "Lamb Biryani" },
  { "id": 352, "name": "Paneer Butter Masala" },
  { "id": 353, "name": "Dal Tadka" },
  { "id": 354, "name": "Chana Masala" },
  { "id": 355, "name": "Rajma" },
  { "id": 356, "name": "Aloo Gobi" },
  { "id": 357, "name": "Baingan Bharta" },
  { "id": 358, "name": "Pav Bhaji" },
  { "id": 359, "name": "Dhokla" },
  { "id": 360, "name": "Khandvi" },
  { "id": 361, "name": "Vada Pav" },
  { "id": 362, "name": "Misal Pav" },
  { "id": 363, "name": "Sabudana Khichdi" },
  { "id": 364, "name": "Masala Dosa" },
  { "id": 365, "name": "Idli" },
  { "id": 366, "name": "Uttapam" },
  { "id": 367, "name": "Sambar" },
  { "id": 368, "name": "Rasam" },
  { "id": 369, "name": "Malai Kofta" },
  { "id": 370, "name": "Butter Chicken" },
  { "id": 371, "name": "Tandoori Chicken" },
  { "id": 372, "name": "Seekh Kebab" },
  { "id": 373, "name": "Naan" },
  { "id": 374, "name": "Garlic Naan" },
  { "id": 375, "name": "Roti" },
  { "id": 376, "name": "Paratha" },
  { "id": 377, "name": "Puri" },
  { "id": 378, "name": "Kachori" },
  { "id": 379, "name": "Lassi" },
  { "id": 380, "name": "Rasgulla" },
  { "id": 381, "name": "Gulab Jamun" },
  { "id": 382, "name": "Jalebi" },
  { "id": 383, "name": "Kheer" },
  { "id": 384, "name": "Halwa" },
  { "id": 385, "name": "Basundi" },
  { "id": 386, "name": "Shrikhand" },
  { "id": 387, "name": "Kulfi" },
  { "id": 388, "name": "Mango Lassi" },
  { "id": 389, "name": "Paneer Bhurji" },
  { "id": 390, "name": "Methi Thepla" },
  { "id": 391, "name": "Undhiyu" },
  { "id": 392, "name": "Handvo" },
  { "id": 393, "name": "Bhindi Masala" },
  { "id": 394, "name": "Matar Paneer" },
  { "id": 395, "name": "Moong Dal" },
  { "id": 396, "name": "Tomato Chutney" },
  { "id": 397, "name": "Coconut Chutney" },
  { "id": 398, "name": "Green Chutney" },
  { "id": 399, "name": "Tamarind Chutney" },
  { "id": 400, "name": "Steak" },
  { "id": 401, "name": "Steak Frites" },
  { "id": 402, "name": "Beef Bourguignon" },
  { "id": 403, "name": "Coq au Vin" },
  { "id": 404, "name": "Ratatouille" },
  { "id": 405, "name": "French Dip Sandwich" },
  { "id": 406, "name": "Croque Monsieur" },
  { "id": 407, "name": "Croque Madame" },
  { "id": 408, "name": "Niçoise Salad" },
  { "id": 409, "name": "Soufflé" },
  { "id": 410, "name": "Crème brûlée" },
  { "id": 411, "name": "Chocolate Mousse" },
  { "id": 412, "name": "Eclairs" },
  { "id": 413, "name": "Macarons" },
  { "id": 414, "name": "Madeleines" },
  { "id": 415, "name": "Tarte Tatin" },
  { "id": 416, "name": "Quiche Lorraine" },
  { "id": 417, "name": "Bouillabaisse" },
  { "id": 418, "name": "Cassoulet" },
  { "id": 419, "name": "Salade Lyonnaise" },
  { "id": 420, "name": "Onion Soup Gratinée" },
  { "id": 421, "name": "Gnocchi" },
  { "id": 422, "name": "Panna Cotta" },
  { "id": 423, "name": "Affogato" },
  { "id": 424, "name": "Gelato" },
  { "id": 425, "name": "Arancini" },
  { "id": 426, "name": "Focaccia" },
  { "id": 427, "name": "Polenta" },
  { "id": 428, "name": "Osso Buco" },
  { "id": 429, "name": "Saltimbocca" },
  { "id": 430, "name": "Carpaccio" },
  { "id": 431, "name": "Minestrone Soup" },
  { "id": 432, "name": "Prosciutto e Melone" },
  { "id": 433, "name": "Cannoli" },
  { "id": 434, "name": "Biscotti" },
  { "id": 435, "name": "Zabaglione" },
  { "id": 436, "name": "Spanakopita" },
  { "id": 437, "name": "Souvlaki" },
  { "id": 438, "name": "Gyro" },
  { "id": 439, "name": "Dolmades" },
  { "id": 440, "name": "Avgolemono Soup" },
  { "id": 441, "name": "Taramosalata" },
  { "id": 442, "name": "Tzatziki" },
  { "id": 443, "name": "Stifado" },
  { "id": 444, "name": "Kleftiko" },
  { "id": 445, "name": "Revani" },
  { "id": 446, "name": "Galaktoboureko" },
  { "id": 447, "name": "Patatas Bravas" },
  { "id": 448, "name": "Gambas al Ajillo" },
  { "id": 449, "name": "Tortilla Española" },
  { "id": 450, "name": "Albondigas" },
  { "id": 451, "name": "Pulpo a la Gallega" },
  { "id": 452, "name": "Fabada Asturiana" },
  { "id": 453, "name": "Gazpacho Andaluz" },
  { "id": 454, "name": "Crema Catalana" },
  { "id": 455, "name": "Tarta de Santiago" },
  { "id": 456, "name": "Leche Frita" },
  { "id": 457, "name": "Paella Valenciana" },
  { "id": 458, "name": "Fideuà" },
  { "id": 459, "name": "Migas" },
  { "id": 460, "name": "Pisto" },
  { "id": 461, "name": "Currywurst" },
  { "id": 462, "name": "Spätzle" },
  { "id": 463, "name": "Kartoffelsalat" },
  { "id": 464, "name": "Rouladen" },
  { "id": 465, "name": "Königsberger Klopse" },
  { "id": 466, "name": "Black Forest Cake" },
  { "id": 467, "name": "Apfelstrudel" },
  { "id": 468, "name": "Lebkuchen" },
  { "id": 469, "name": "Stollen" },
  { "id": 470, "name": "Kaiserschmarrn" },
  { "id": 471, "name": "Wiener Schnitzel" },
  { "id": 472, "name": "Tafelspitz" },
  { "id": 473, "name": "Sachertorte" },
  { "id": 474, "name": "Linzer Torte" },
  { "id": 475, "name": "Cheese Fondue" },
  { "id": 476, "name": "Raclette" },
  { "id": 477, "name": "Rösti" },
  { "id": 478, "name": "Zürcher Geschnetzeltes" },
  { "id": 479, "name": "Älplermagronen" },
  { "id": 480, "name": "Birchermüesli" },
  { "id": 481, "name": "Chocolate Fondue" },
  { "id": 482, "name": "Bündner Nusstorte" },
  { "id": 483, "name": "Ćevapi" },
  { "id": 484, "name": "Pljeskavica" },
  { "id": 485, "name": "Sarmale" },
  { "id": 486, "name": "Ajvar" },
  { "id": 487, "name": "Kajmak" },
  { "id": 488, "name": "Shopska Salad" },
  { "id": 489, "name": "Tarator" },
  { "id": 490, "name": "Banitsa" },
  { "id": 491, "name": "Musaca" },
  { "id": 492, "name": "Gibanica" },
  { "id": 493, "name": "Kifli" },
  { "id": 494, "name": "Chicken Paprikash" },
  { "id": 495, "name": "Halászlé" },
  { "id": 496, "name": "Lángos" },
  { "id": 497, "name": "Dobos Torte" },
  { "id": 498, "name": "Kürtőskalács" },
  { "id": 499, "name": "Pogača" },
  { "id": 500, "name": "Bigos" },
  { "id": 501, "name": "Jollof Rice" },
  { "id": 502, "name": "Tagine" },
  { "id": 503, "name": "Shakshuka" },
  { "id": 504, "name": "Baba Ghanoush" },
  { "id": 505, "name": "Fattoush" },
  { "id": 506, "name": "Kibbeh" },
  { "id": 507, "name": "Mansaf" },
  { "id": 508, "name": "Kabsa" },
  { "id": 509, "name": "Mujadara" },
  { "id": 510, "name": "Maqluba" },
  { "id": 511, "name": "Ful Medames" },
  { "id": 512, "name": "Koshary" },
  { "id": 513, "name": "Molokhia" },
  { "id": 514, "name": "Umm Ali" },
  { "id": 515, "name": "Kunafa" },
  { "id": 516, "name": "Basbousa" },
  { "id": 517, "name": "Luqaimat" },
  { "id": 518, "name": "Harira" },
  { "id": 519, "name": "Bissara" },
  { "id": 520, "name": "Chermoula Fish" },
  { "id": 521, "name": "Pastilla" },
  { "id": 522, "name": "Thieboudienne" },
  { "id": 523, "name": "Chicken Yassa" },
  { "id": 524, "name": "Mafé" },
  { "id": 525, "name": "Attiéké" },
  { "id": 526, "name": "Injera with Doro Wat" },
  { "id": 527, "name": "Tibs" },
  { "id": 528, "name": "Kitfo" },
  { "id": 529, "name": "Shiro Wat" },
  { "id": 530, "name": "Genfo" },
  { "id": 531, "name": "Nyama Choma" },
  { "id": 532, "name": "Ugali" },
  { "id": 533, "name": "Sukuma Wiki" },
  { "id": 534, "name": "Kachumbari" },
  { "id": 535, "name": "Pilau" },
  { "id": 536, "name": "Chapati" },
  { "id": 537, "name": "Mandazi" },
  { "id": 538, "name": "Bunny Chow" },
  { "id": 539, "name": "Bobotie" },
  { "id": 540, "name": "Chakalaka" },
  { "id": 541, "name": "Pap en Vleis" },
  { "id": 542, "name": "Vetkoek" },
  { "id": 543, "name": "Malva Pudding" },
  { "id": 544, "name": "Koeksisters" },
  { "id": 545, "name": "Biltong" },
  { "id": 546, "name": "Droëwors" },
  { "id": 547, "name": "Sosaties" },
  { "id": 548, "name": "Plov" },
  { "id": 549, "name": "Laghman" },
  { "id": 550, "name": "Manti" },
  { "id": 551, "name": "Beshbarmak" },
  { "id": 552, "name": "Samsa" },
  { "id": 553, "name": "Shashlik" },
  { "id": 554, "name": "Lepyoshka" },
  { "id": 555, "name": "Shorpo" },
  { "id": 556, "name": "Kazy" },
  { "id": 557, "name": "Chak-Chak" },
  { "id": 558, "name": "Sumalak" },
  { "id": 559, "name": "Feijoada" },
  { "id": 560, "name": "Moqueca" },
  { "id": 561, "name": "Pão de Queijo" },
  { "id": 562, "name": "Coxinha" },
  { "id": 563, "name": "Brigadeiro" },
  { "id": 564, "name": "Acarajé" },
  { "id": 565, "name": "Vatapá" },
  { "id": 566, "name": "Farofa" },
  { "id": 567, "name": "Churrasco" },
  { "id": 568, "name": "Chimichurri Steak" },
  { "id": 569, "name": "Asado" },
  { "id": 570, "name": "Milanesa" },
  { "id": 571, "name": "Locro" },
  { "id": 572, "name": "Choripán" },
  { "id": 573, "name": "Alfajores" },
  { "id": 574, "name": "Dulce de Leche" },
  { "id": 575, "name": "Pastel de Choclo" },
  { "id": 576, "name": "Sopaipillas" },
  { "id": 577, "name": "Curanto" },
  { "id": 578, "name": "Pebre" },
  { "id": 579, "name": "Arepas" },
  { "id": 580, "name": "Pabellón Criollo" },
  { "id": 581, "name": "Hallaca" },
  { "id": 582, "name": "Tequeños" },
  { "id": 583, "name": "Cachapa" },
  { "id": 584, "name": "Bandeja Paisa" },
  { "id": 585, "name": "Ajiaco" },
  { "id": 586, "name": "Sancocho" },
  { "id": 587, "name": "Patacones" },
  { "id": 588, "name": "Lomo Saltado" },
  { "id": 589, "name": "Aji de Gallina" },
  { "id": 590, "name": "Papa a la Huancaína" },
  { "id": 591, "name": "Anticuchos" },
  { "id": 592, "name": "Rocoto Relleno" },
  { "id": 593, "name": "Picarones" },
  { "id": 594, "name": "Suspiro a la Limeña" },
  { "id": 595, "name": "Llapingachos" },
  { "id": 596, "name": "Fanesca" },
  { "id": 597, "name": "Encebollado" },
  { "id": 598, "name": "Seco de Chivo" },
  { "id": 599, "name": "Humitas" },
  { "id": 600, "name": "Quimbolitos" },
  { "id": 601, "name": "Jerk Chicken" },
  { "id": 602, "name": "Rice and Peas" },
  { "id": 603, "name": "Ackee and Saltfish" },
  { "id": 604, "name": "Callaloo" },
  { "id": 605, "name": "Doubles" },
  { "id": 606, "name": "Roti" },
  { "id": 607, "name": "Escovitch Fish" },
  { "id": 608, "name": "Jamaican Patty" },
  { "id": 609, "name": "Conch Fritters" },
  { "id": 610, "name": "Rum Cake" },
  { "id": 611, "name": "Fried Plantains" },
  { "id": 612, "name": "Mofongo" },
  { "id": 613, "name": "Arroz con Gandules" },
  { "id": 614, "name": "Pernil" },
  { "id": 615, "name": "Tembleque" },
  { "id": 616, "name": "Coquito" },
  { "id": 617, "name": "Souse" },
  { "id": 618, "name": "Pelau" },
  { "id": 619, "name": "Oil Down" },
  { "id": 620, "name": "Cou-Cou and Flying Fish" },
  { "id": 621, "name": "La Bandera Dominicana" },
  { "id": 622, "name": "Mangú" },
  { "id": 623, "name": "Sancocho Dominicano" },
  { "id": 624, "name": "Chivo Guisado" },
  { "id": 625, "name": "Habichuelas con Dulce" },
  { "id": 626, "name": "Ropa Vieja" },
  { "id": 627, "name": "Moros y Cristianos" },
  { "id": 628, "name": "Picadillo" },
  { "id": 629, "name": "Yuca con Mojo" },
  { "id": 630, "name": "Flan" },
  { "id": 631, "name": "Arroz con Pollo" },
  { "id": 632, "name": "Lechón Asado" },
  { "id": 633, "name": "Tamales" },
  { "id": 634, "name": "Pozole" },
  { "id": 635, "name": "Mole Poblano" },
  { "id": 636, "name": "Chiles Rellenos" },
  { "id": 637, "name": "Sopa de Tortilla" },
  { "id": 638, "name": "Elote" },
  { "id": 639, "name": "Cochinita Pibil" },
  { "id": 640, "name": "Aguas Frescas" },
  { "id": 641, "name": "Horchata" },
  { "id": 642, "name": "Cake" },
  { "id": 643, "name": "Pan de Muerto" },
  { "id": 644, "name": "Rosca de Reyes" },
  { "id": 645, "name": "Menudo" },
  { "id": 646, "name": "Birria Tacos" },
  { "id": 647, "name": "Carnitas Tacos" },
  { "id": 648, "name": "Tacos al Pastor" },
  { "id": 649, "name": "Barbacoa Tacos" },
  { "id": 650, "name": "Chicharrón" },
  { "id": 651, "name": "Queso Fundido" },
  { "id": 652, "name": "Frijoles Charros" },
  { "id": 653, "name": "Arroz con Leche" },
  { "id": 654, "name": "Natillas" },
  { "id": 655, "name": "Polvorones" },
  { "id": 656, "name": "Mantecados" },
  { "id": 657, "name": "Turrón" },
  { "id": 658, "name": "Marzipan Fruits" },
  { "id": 659, "name": "Gravlax" },
  { "id": 660, "name": "Swedish Meatballs with Cream Sauce" },
  { "id": 661, "name": "Smørrebrød" },
  { "id": 662, "name": "Pickled Herring" },
  { "id": 663, "name": "Janssons Frestelse" },
  { "id": 664, "name": "Scandinavian Pea Soup" },
  { "id": 665, "name": "Köttbullar" },
  { "id": 666, "name": "Surströmming" },
  { "id": 667, "name": "Palt" },
  { "id": 668, "name": "Kroppkakor" },
  { "id": 669, "name": "Semla" },
  { "id": 670, "name": "Kanelbulle" },
  { "id": 671, "name": "Lefse" },
  { "id": 672, "name": "Lutefisk" },
  { "id": 673, "name": "Fårikål" },
  { "id": 674, "name": "Krumkake" },
  { "id": 675, "name": "Kransekake" },
  { "id": 676, "name": "Rugbrød" },
  { "id": 677, "name": "Frikadeller" },
  { "id": 678, "name": "Leverpostej" },
  { "id": 679, "name": "Æblekage" },
  { "id": 680, "name": "Pumpernickel" },
  { "id": 681, "name": "Labskaus" },
  { "id": 682, "name": "Rollmops" },
  { "id": 683, "name": "Matjes Herring" },
  { "id": 684, "name": "Himmel und Erde" },
  { "id": 685, "name": "Grünkohl mit Pinkel" },
  { "id": 686, "name": "Zrazy" },
  { "id": 687, "name": "Kotlet Schabowy" },
  { "id": 688, "name": "Żurek" },
  { "id": 689, "name": "Gołąbki" },
  { "id": 690, "name": "Sernik" },
  { "id": 691, "name": "Makowiec" },
  { "id": 692, "name": "Oscypek" },
  { "id": 693, "name": "Bryndzové Halušky" },
  { "id": 694, "name": "Segedínsky Guláš" },
  { "id": 695, "name": "Svíčková" },
  { "id": 696, "name": "Trdelník" },
  { "id": 697, "name": "Vepřo Knedlo Zelo" },
  { "id": 698, "name": "Knish" },
  { "id": 699, "name": "Latkes" },
  { "id": 700, "name": "Matzah Ball Soup" },
  { "id": 701, "name": "Xiaolongbao" },
  { "id": 702, "name": "Tanghulu" },
  { "id": 703, "name": "Mooncake" },
  { "id": 704, "name": "Zongzi" },
  { "id": 705, "name": "Jianbing" },
  { "id": 706, "name": "Roujiamo" },
  { "id": 707, "name": "Hot Pot" },
  { "id": 708, "name": "Mapo Tofu" },
  { "id": 709, "name": "Kung Pao Chicken" },
  { "id": 710, "name": "Sichuan Boiled Beef" },
  { "id": 711, "name": "Dan Dan Noodles" },
  { "id": 712, "name": "Twice Cooked Pork" },
  { "id": 713, "name": "Beggar's Chicken" },
  { "id": 714, "name": "Char Siu" },
  { "id": 715, "name": "Congee" },
  { "id": 716, "name": "Youtiao" },
  { "id": 717, "name": "Douhua" },
  { "id": 718, "name": "Bubble Tea" },
  { "id": 719, "name": "Mango Sticky Rice" },
  { "id": 720, "name": "Green Curry" },
  { "id": 721, "name": "Red Curry" },
  { "id": 722, "name": "Massaman Curry" },
  { "id": 723, "name": "Panang Curry" },
  { "id": 724, "name": "Som Tum" },
  { "id": 725, "name": "Larb" },
  { "id": 726, "name": "Khao Soi" },
  { "id": 727, "name": "Pad See Ew" },
  { "id": 728, "name": "PB & J Sandwich" },
  { "id": 729, "name": "Tom Kha Gai" },
  { "id": 730, "name": "Pineapple Fried Rice" },
  { "id": 731, "name": "Mi Krop" },
  { "id": 732, "name": "Chicken Satay with Peanut Sauce" },
  { "id": 733, "name": "Peanut Butter and Jelly Sandwich" },
  { "id": 734, "name": "Gudeg" },
  { "id": 735, "name": "Pempek" },
  { "id": 736, "name": "Ketoprak" },
  { "id": 737, "name": "Asinan Sayur" },
  { "id": 738, "name": "Cendol" },
  { "id": 739, "name": "Es Doger" },
  { "id": 740, "name": "Klepon" },
  { "id": 741, "name": "Lemper" },
  { "id": 742, "name": "Banh Bot Loc" },
  { "id": 743, "name": "Cao Lau" },
  { "id": 744, "name": "Banh Cuon" },
  { "id": 745, "name": "Bobun" },
  { "id": 746, "name": "Mohinga" },
  { "id": 747, "name": "Lahpet Thoke" },
  { "id": 748, "name": "Ohn No Khao Swè" },
  { "id": 749, "name": "Khao Poon" },
  { "id": 750, "name": "Sinigang na Baboy" },
  { "id": 751, "name": "Chicken Adobo" },
  { "id": 752, "name": "Pork Adobo" },
  { "id": 753, "name": "Pancit Palabok" },
  { "id": 754, "name": "Pancit Bihon" },
  { "id": 755, "name": "La Paz Batchoy" },
  { "id": 756, "name": "Sisig" },
  { "id": 757, "name": "Dinuguan" },
  { "id": 758, "name": "Pinakbet" },
  { "id": 759, "name": "Bulalo" },
  { "id": 760, "name": "Arroz Caldo" },
  { "id": 761, "name": "Champorado" },
  { "id": 762, "name": "Ube Halaya" },
  { "id": 763, "name": "Leche Flan" },
  { "id": 764, "name": "Polvoron" },
  { "id": 765, "name": "Monjayaki" },
  { "id": 766, "name": "Nikujaga" },
  { "id": 767, "name": "Chawanmushi" },
  { "id": 768, "name": "Agedashi Tofu" },
  { "id": 769, "name": "Edamame" },
  { "id": 770, "name": "Onigiri" },
  { "id": 771, "name": "Haleem" },
  { "id": 772, "name": "Dorayaki" },
  { "id": 773, "name": "Taiyaki" },
  { "id": 774, "name": "Anmitsu" },
  { "id": 775, "name": "Kakigori" },
  { "id": 776, "name": "Dango" },
  { "id": 777, "name": "Senbei" },
  { "id": 778, "name": "Sukiyaki" },
  { "id": 779, "name": "Shabu-shabu" },
  { "id": 780, "name": "Zaru Soba" },
  { "id": 781, "name": "Hoto Noodles" },
  { "id": 782, "name": "Champon" },
  { "id": 783, "name": "Hitsumabushi" },
  { "id": 784, "name": "Oden" },
  { "id": 785, "name": "Fugu Sashimi" },
  { "id": 786, "name": "Mul Naengmyeon" },
  { "id": 787, "name": "Bibim Naengmyeon" },
  { "id": 788, "name": "Bossam" },
  { "id": 789, "name": "Jokbal" },
  { "id": 790, "name": "Anju" },
  { "id": 791, "name": "Gyeranmari" },
  { "id": 792, "name": "Kimchi Pajeon" },
  { "id": 793, "name": "Sujeonggwa" },
  { "id": 794, "name": "Sikhye" },
  { "id": 795, "name": "Bingsu" },
  { "id": 796, "name": "Yakgwa" },
  { "id": 797, "name": "Songpyeon" },
  { "id": 798, "name": "Chapssaltteok" },
  { "id": 799, "name": "Patbingsu" },
  { "id": 800, "name": "Dolsot Bibimbap" },
  { "id": 801, "name": "Cottage Pie" },
  { "id": 802, "name": "Steak and Kidney Pie" },
  { "id": 803, "name": "Chicken and Rice" },
  { "id": 804, "name": "Ploughman's Lunch" },
  { "id": 805, "name": "Bubble and Squeak" },
  { "id": 806, "name": "Kedgeree" },
  { "id": 807, "name": "Eton Mess" },
  { "id": 808, "name": "Banoffee Pie" },
  { "id": 809, "name": "Trifle" },
  { "id": 810, "name": "Oatmeal" },
  { "id": 811, "name": "Bread and Butter Pudding" },
  { "id": 812, "name": "Summer Pudding" },
  { "id": 813, "name": "Welsh Cakes" },
  { "id": 814, "name": "Bara Brith" },
  { "id": 815, "name": "Cawl" },
  { "id": 816, "name": "Chicken and Waffles" },
  { "id": 817, "name": "Lancashire Hotpot" },
  { "id": 818, "name": "Scouse" },
  { "id": 819, "name": "Pease Pudding" },
  { "id": 820, "name": "Stargazy Pie" },
  { "id": 821, "name": "Cullen Skink" },
  { "id": 822, "name": "Smoothie" },
  { "id": 823, "name": "Forfar Bridie" },
  { "id": 824, "name": "Steamed Cockles" },
  { "id": 825, "name": "Moules Marinières" },
  { "id": 826, "name": "Raw Oysters" },
  { "id": 827, "name": "Seared Scallops" },
  { "id": 828, "name": "Fishcakes" },
  { "id": 829, "name": "Crab Cakes" },
  { "id": 830, "name": "Lobster Bisque" },
  { "id": 831, "name": "Shrimp Cocktail" },
  { "id": 832, "name": "Waldorf Salad" },
  { "id": 833, "name": "Olivier Salad" },
  { "id": 834, "name": "Potato Gratin" },
  { "id": 835, "name": "Hasselback Potatoes" },
  { "id": 836, "name": "Roasted Potatoes" },
  { "id": 837, "name": "Jacket Potato" },
  { "id": 838, "name": "Lyonnaise Potatoes" },
  { "id": 839, "name": "Champ" },
  { "id": 840, "name": "Rumbledethumps" },
  { "id": 841, "name": "Pan Haggerty" },
  { "id": 842, "name": "Boiled New Potatoes" },
  { "id": 843, "name": "Steamed Asparagus" },
  { "id": 844, "name": "Grilled Corn on the Cob" },
  { "id": 845, "name": "Roasted Root Vegetables" },
  { "id": 846, "name": "Vegetable Tian" },
  { "id": 847, "name": "Stuffed Artichokes" },
  { "id": 848, "name": "Stuffed Mushrooms" },
  { "id": 849, "name": "Stuffed Cabbage Rolls" },
  { "id": 850, "name": "Braised Collard Greens" },
  { "id": 851, "name": "Creamed Spinach" },
  { "id": 852, "name": "Corn Fritters" },
  { "id": 853, "name": "Zucchini Fritters" },
  { "id": 854, "name": "Onion Bhaji" },
  { "id": 855, "name": "Vegetable Pakora" },
  { "id": 856, "name": "Paneer Pakora" },
  { "id": 857, "name": "Aloo Tikki Chaat" },
  { "id": 858, "name": "Dahi Vada" },
  { "id": 859, "name": "Papri Chaat" },
  { "id": 860, "name": "Bhel Puri" },
  { "id": 861, "name": "Sev Puri" },
  { "id": 862, "name": "Pani Puri" },
  { "id": 863, "name": "Idiyappam" },
  { "id": 864, "name": "Appam with Stew" },
  { "id": 865, "name": "Puttu with Kadala Curry" },
  { "id": 866, "name": "Rava Upma" },
  { "id": 867, "name": "Kande Pohe" },
  { "id": 868, "name": "Aloo Paratha" },
  { "id": 869, "name": "Moong Dal Khichdi" },
  { "id": 870, "name": "Vegetable Pulao" },
  { "id": 871, "name": "Lemon Rice" },
  { "id": 872, "name": "Curd Rice" },
  { "id": 873, "name": "Tamarind Rice" },
  { "id": 874, "name": "Coconut Rice" },
  { "id": 875, "name": "Jeera Rice" },
  { "id": 876, "name": "Dodo" },
  { "id": 877, "name": "Suya" },
  { "id": 878, "name": "Efo Riro" },
  { "id": 879, "name": "Egusi Soup" },
  { "id": 880, "name": "Pepper Soup" },
  { "id": 881, "name": "Ogbono Soup" },
  { "id": 882, "name": "Fufu" },
  { "id": 883, "name": "Banku with Tilapia" },
  { "id": 884, "name": "Kenkey with Fried Fish" },
  { "id": 885, "name": "Waakye" },
  { "id": 886, "name": "Red Red" },
  { "id": 887, "name": "Groundnut Soup" },
  { "id": 888, "name": "Cachupa" },
  { "id": 889, "name": "Kulebyaka" },
  { "id": 890, "name": "Solyanka" },
  { "id": 891, "name": "Okroshka" },
  { "id": 892, "name": "Draniki" },
  { "id": 893, "name": "Syrniki" },
  { "id": 894, "name": "Golubtsy" },
  { "id": 895, "name": "Buckwheat Kasha" },
  { "id": 896, "name": "Vinegret" },
  { "id": 897, "name": "Overnight Oats" },
  { "id": 898, "name": "Mimosa Salad" },
  { "id": 899, "name": "Khachapuri Adjaruli" },
  { "id": 900, "name": "Lobio" },
  { "id": 901, "name": "Pkhali" },
  { "id": 902, "name": "Churchkhela" },
  { "id": 903, "name": "Tkemali Sauce" },
  { "id": 904, "name": "Satsivi" },
  { "id": 905, "name": "Chkmeruli" },
  { "id": 906, "name": "Waterzooi" },
  { "id": 907, "name": "Stoemp" },
  { "id": 908, "name": "Carbonnade Flamande" },
  { "id": 909, "name": "Brussels Waffle" },
  { "id": 910, "name": "Dame Blanche" },
  { "id": 911, "name": "Cookies" },
  { "id": 912, "name": "Poffertjes" },
  { "id": 913, "name": "Stamppot Boerenkool" },
  { "id": 914, "name": "Hutspot" },
  { "id": 915, "name": "Erwtensoep" },
  { "id": 916, "name": "Bitterballen" },
  { "id": 917, "name": "Kroketten" },
  { "id": 918, "name": "Hollandse Nieuwe Haring" },
  { "id": 919, "name": "Tompouce" },
  { "id": 920, "name": "Stroopwafel" },
  { "id": 921, "name": "Kibbeling" },
  { "id": 922, "name": "Patatje Oorlog" },
  { "id": 923, "name": "Lamb Chops" },
  { "id": 924, "name": "Pork Chops" },
  { "id": 925, "name": "Ribeye Steak" },
  { "id": 926, "name": "Roast Leg of Lamb" },
  { "id": 927, "name": "Grilled Salmon Fillet" },
  { "id": 928, "name": "Baked Cod" },
  { "id": 929, "name": "Seared Tuna Steak" },
  { "id": 930, "name": "Grilled Swordfish" },
  { "id": 931, "name": "Fish Chowder" },
  { "id": 932, "name": "Baked Salmon" },
  { "id": 933, "name": "Cioppino" },
  { "id": 934, "name": "Arroz de Marisco" },
  { "id": 935, "name": "Bacalhau à Brás" },
  { "id": 936, "name": "Caldo Verde" },
  { "id": 937, "name": "Francesinha" },
  { "id": 938, "name": "Pastel de Nata" },
  { "id": 939, "name": "Piri Piri Chicken" },
  { "id": 940, "name": "Bifana" },
  { "id": 941, "name": "Amêijoas à Bulhão Pato" },
  { "id": 942, "name": "Polvo à Lagareiro" },
  { "id": 943, "name": "Migas Alentejanas" },
  { "id": 944, "name": "Açorda de Marisco" },
  { "id": 945, "name": "Toucinho do Céu" },
  { "id": 946, "name": "Sericaia" },
  { "id": 947, "name": "Fresh Fruit Salad" },
  { "id": 948, "name": "Ambrosia Salad" },
  { "id": 949, "name": "Jello Mold" },
  { "id": 950, "name": "Popcorn" },
  { "id": 951, "name": "Trail Mix" },
  { "id": 952, "name": "Granola with Yogurt" },
  { "id": 953, "name": "Porridge" },
  { "id": 954, "name": "Cream of Wheat" },
  { "id": 955, "name": "Cereal" },
  { "id": 956, "name": "Cornmeal Mush" },
  { "id": 957, "name": "Chicken Masala" },
  { "id": 958, "name": "Cheese Blintzes" },
  { "id": 959, "name": "Crêpes Suzette" },
  { "id": 960, "name": "Belgian Fries with Andalouse Sauce" },
  { "id": 961, "name": "Sweet Potato Fries" },
  { "id": 962, "name": "Potato Wedges" },
  { "id": 963, "name": "Tater Tots" },
  { "id": 964, "name": "Hash Brown" },
  { "id": 965, "name": "Blooming Onion" },
  { "id": 966, "name": "Coleslaw" },
  { "id": 967, "name": "Macaroni Salad" },
  { "id": 968, "name": "Nutella Sandwich" },
  { "id": 969, "name": "Cucumber Dill Salad" },
  { "id": 970, "name": "Tomato, Onion, and Basil Salad" },
  { "id": 971, "name": "Apple Crumble" },
  { "id": 972, "name": "Peach Cobbler" },
  { "id": 973, "name": "Chocolate Bread Pudding" },
  { "id": 974, "name": "Tapioca Pudding" },
  { "id": 975, "name": "Chocolate Pudding Pie" },
  { "id": 976, "name": "Vanilla Bean Pudding" },
  { "id": 977, "name": "Butterscotch Pudding" },
  { "id": 978, "name": "Halva" },
  { "id": 979, "name": "Pavlova with Berries" },
  { "id": 980, "name": "Lamingtons" },
  { "id": 981, "name": "Biscuits" },
  { "id": 982, "name": "Tim Tam Slam" },
  { "id": 983, "name": "Fairy Bread" },
  { "id": 984, "name": "Vegemite on Toast" },
  { "id": 985, "name": "Australian Meat Pie" },
  { "id": 986, "name": "Sausage Rolls" },
  { "id": 987, "name": "Fried Calamari Rings" },
  { "id": 988, "name": "Whitebait Fritters" },
  { "id": 989, "name": "Hangi Meal" },
  { "id": 990, "name": "Banana Bread" },
  { "id": 991, "name": "Afghan Biscuits" },
  { "id": 992, "name": "Southland Cheese Rolls" },
  { "id": 993, "name": "Rice Pudding" },
  { "id": 994, "name": "Pastitsio" },
  { "id": 995, "name": "Yemistes" },
  { "id": 996, "name": "Fasolada" },
  { "id": 997, "name": "Koulourakia" },
  { "id": 998, "name": "Melomakarona" },
  { "id": 999, "name": "Kourabiedes" },
  { "id": 1000, "name": "Toast" },
  { "id": 1001, "name": "Breakfast Wrap" },
  { "id": 1002, "name": "Egg Salad" },
  { "id": 1003, "name": "Egg Salad Sandwich" }
]
